{
  "tree": {
    "type": "View",
    "id": "parity_view",
    "attributes": {
      "style": "width: 100%",
      "title": "CoreUI Parity Test"
    },
    "children": [
      {
        "type": "Grid",
        "id": "parity_grid",
        "attributes": {
          "cols": [
            "1*",
            "250px"
          ],
          "gap": "24px"
        },
        "children": [
          {
            "type": "Stack",
            "id": "main_stack",
            "attributes": {
              "dir": "v",
              "gap": "18px"
            },
            "children": [
              {
                "type": "Stack",
                "id": "toolbar_stack",
                "attributes": {
                  "align": "center",
                  "dir": "h",
                  "gap": "12px"
                },
                "children": [
                  {
                    "type": "Text",
                    "id": "status_text",
                    "attributes": {
                      "size": "26px",
                      "style": "color: primary",
                      "value": "Renderer Parity",
                      "weight": "bold"
                    }
                  },
                  {
                    "type": "Trigger",
                    "id": "sync_trigger",
                    "attributes": {
                      "action": {
                        "call": "notify",
                        "namespace": "app",
                        "params": {
                          "msg": "Sync Complete",
                          "type": "success"
                        }
                      },
                      "label": "Run Sync"
                    }
                  }
                ]
              },
              {
                "type": "Box",
                "id": "content_box",
                "attributes": {
                  "background": "surface",
                  "padding": "20px",
                  "style": "width: 100%"
                },
                "children": [
                  {
                    "type": "Input",
                    "id": "search_input",
                    "attributes": {
                      "bind": "query",
                      "label": "Search",
                      "type": "text"
                    }
                  },
                  {
                    "type": "DataTable",
                    "id": "results_table",
                    "attributes": {
                      "selectable": true,
                      "source": "results"
                    }
                  }
                ]
              }
            ]
          },
          {
            "type": "Box",
            "id": "sidebar_box",
            "attributes": {
              "background": "panel",
              "padding": "16px"
            },
            "children": [
              {
                "type": "Text",
                "id": "sidebar_title",
                "attributes": {
                  "size": "18px",
                  "style": "color: accent",
                  "value": "Summary",
                  "weight": "bold"
                }
              },
              {
                "type": "Text",
                "id": "sidebar_copy",
                "attributes": {
                  "value": "Mixing px, %, and fractional units in one layout."
                }
              }
            ]
          }
        ]
      }
    ]
  },
  "index": {
    "content_box": {
      "path": "/tree/children/0/children/0/children/1",
      "type": "Box"
    },
    "main_stack": {
      "path": "/tree/children/0/children/0",
      "type": "Stack"
    },
    "parity_grid": {
      "path": "/tree/children/0",
      "type": "Grid"
    },
    "parity_view": {
      "path": "/tree",
      "type": "View"
    },
    "results_table": {
      "path": "/tree/children/0/children/0/children/1/children/1",
      "type": "DataTable"
    },
    "search_input": {
      "path": "/tree/children/0/children/0/children/1/children/0",
      "type": "Input"
    },
    "sidebar_box": {
      "path": "/tree/children/0/children/1",
      "type": "Box"
    },
    "sidebar_copy": {
      "path": "/tree/children/0/children/1/children/1",
      "type": "Text"
    },
    "sidebar_title": {
      "path": "/tree/children/0/children/1/children/0",
      "type": "Text"
    },
    "status_text": {
      "path": "/tree/children/0/children/0/children/0/children/0",
      "type": "Text"
    },
    "sync_trigger": {
      "path": "/tree/children/0/children/0/children/0/children/1",
      "type": "Trigger"
    },
    "toolbar_stack": {
      "path": "/tree/children/0/children/0/children/0",
      "type": "Stack"
    }
  },
  "theme": {
    "accent": "#00b894",
    "panel": "#dfe6e9",
    "primary": "#0984e3",
    "surface": "#f5f6fa"
  },
  "metadata": {
    "compiled_at": "2026-04-26T05:38:43Z",
    "version": "dev",
    "registry_version": "1.2.0"
  }
}
